rp3_cache/Manager.py
rp3_cache/Utils.py
rp3_cache/__init__.py
rp3_cache/conf/default.yaml
test/__init__.py
test/test_Manager.py
test/test_Utils.py
rp3_cache-1.2.dist-info/LICENSE
rp3_cache-1.2.dist-info/METADATA
rp3_cache-1.2.dist-info/WHEEL
rp3_cache-1.2.dist-info/top_level.txt
rp3_cache-1.2.dist-info/RECORD
