Metadata-Version: 2.1
Name: rp3-cache
Version: 1.2
Summary: Cache to dope the result retrieval from reaction rules, to be used with RetroPath 3.0
Home-page: https://github.com/brsynth/rp3_cache
Author: Thomas Duigou
Author-email: thomas.duigou@inra.fr
License: UNKNOWN
Platform: UNKNOWN
Requires-Python: >=3.6
